MakeOrBreak/__init__.py
MakeOrBreak/app.py
MakeOrBreak/config.py
MakeOrBreak/configurations.py
MakeOrBreak/controller.py
MakeOrBreak/data.json
MakeOrBreak/dataReader.py
MakeOrBreak/main.py
MakeOrBreak/mappings.py
MakeOrBreak/notifications.py
MakeOrBreak/randomNumberGenerator.py
MakeOrBreak/utils.py
MakeOrBreak/Exceptions/InvalidInputException.py
MakeOrBreak/Exceptions/InvalidOSException.py
MakeOrBreak/Exceptions/__init__.py
MakeOrBreak-1.2.1.dist-info/LICENSE.txt
MakeOrBreak-1.2.1.dist-info/METADATA
MakeOrBreak-1.2.1.dist-info/WHEEL
MakeOrBreak-1.2.1.dist-info/entry_points.txt
MakeOrBreak-1.2.1.dist-info/top_level.txt
MakeOrBreak-1.2.1.dist-info/RECORD
