Metadata-Version: 2.1
Name: MakeOrBreak
Version: 1.2.1
Author: 4_Stooges
Author-email: jorwong5@gmail.com
License: MIT
Classifier: Programming Language :: Python :: 3
Classifier: License :: OSI Approved :: MIT License
Classifier: Operating System :: OS Independent
License-File: LICENSE.txt
